coverage.svg
katapy/__init__.py
katapy/precommit.py
katapy/program.py
katapy/tasks.py
katapy/tox.ini
katapy/tox.py
katapy-0.1.1.dist-info/entry_points.txt
katapy-0.1.1.dist-info/LICENSE
katapy-0.1.1.dist-info/WHEEL
katapy-0.1.1.dist-info/METADATA
katapy-0.1.1.dist-info/RECORD
