Metadata-Version: 2.1
Name: katapy
Version: 0.1.1
Summary: A tool for assisting python developers
Home-page: https://github.com/91nunocosta/katapy
License: MIT
Author: Nuno Costa
Author-email: 91nunocosta@gmail.com
Requires-Python: >=3.9,<4.0
Classifier: License :: OSI Approved :: MIT License
Classifier: Programming Language :: Python :: 3
Classifier: Programming Language :: Python :: 3.10
Classifier: Programming Language :: Python :: 3.9
Requires-Dist: invoke (>=1.6.0,<2.0.0)
Requires-Dist: pre-commit (>=2.15.0,<3.0.0)
Requires-Dist: tox (>=3.24.4,<4.0.0)
Project-URL: Repository, https://github.com/91nunocosta/katapy
